jupyterlab_biolm/__init__.py
jupyterlab_biolm/_hatchling.py
jupyterlab_biolm/serverextension.py
jupyterlab_biolm-1.2.0.data/data/etc/jupyter/jupyter_server_config.d/jupyterlab-biolm.json
jupyterlab_biolm-1.2.0.data/data/share/jupyter/labextensions/jupyterlab-biolm/package.json
jupyterlab_biolm-1.2.0.data/data/share/jupyter/labextensions/jupyterlab-biolm/schemas/jupyterlab-biolm/package.json.orig
jupyterlab_biolm-1.2.0.data/data/share/jupyter/labextensions/jupyterlab-biolm/schemas/jupyterlab-biolm/plugin.json
jupyterlab_biolm-1.2.0.data/data/share/jupyter/labextensions/jupyterlab-biolm/static/462.26eef2cc68d48d263539.js
jupyterlab_biolm-1.2.0.data/data/share/jupyter/labextensions/jupyterlab-biolm/static/665.57bb7975881a83531c46.js
jupyterlab_biolm-1.2.0.data/data/share/jupyter/labextensions/jupyterlab-biolm/static/remoteEntry.8d19a58608019bf31dd9.js
jupyterlab_biolm-1.2.0.data/data/share/jupyter/labextensions/jupyterlab-biolm/static/style.js
jupyterlab_biolm-1.2.0.data/data/share/jupyter/labextensions/jupyterlab-biolm/static/third-party-licenses.json
jupyterlab_biolm-1.2.0.data/data/share/jupyter/lab/schemas/jupyterlab-biolm/plugin.json
jupyterlab_biolm-1.2.0.data/data/share/jupyter/labextensions/jupyterlab-biolm/install.json
jupyterlab_biolm-1.2.0.dist-info/METADATA
jupyterlab_biolm-1.2.0.dist-info/WHEEL
jupyterlab_biolm-1.2.0.dist-info/RECORD
