Metadata-Version: 2.4
Name: jupyterlab-biolm
Version: 1.2.0
Summary: JupyterLab extension for BioLM API integration
Project-URL: Homepage, https://github.com/BioLM/jupyterlab-biolm
Project-URL: Repository, https://github.com/BioLM/jupyterlab-biolm
Project-URL: Issues, https://github.com/BioLM/jupyterlab-biolm/issues
Project-URL: Documentation, https://github.com/BioLM/jupyterlab-biolm
Author: BioLM
License: BSD-3-Clause
Keywords: BioLM,Jupyter,JupyterLab,JupyterLab Extension
Classifier: Framework :: Jupyter
Classifier: Framework :: Jupyter :: JupyterLab
Classifier: Framework :: Jupyter :: JupyterLab :: 4
Classifier: Framework :: Jupyter :: JupyterLab :: Extensions
Classifier: Framework :: Jupyter :: JupyterLab :: Extensions :: Prebuilt
Classifier: License :: OSI Approved :: BSD License
Classifier: Programming Language :: Python
Classifier: Programming Language :: Python :: 3
Classifier: Programming Language :: Python :: 3.8
Classifier: Programming Language :: Python :: 3.9
Classifier: Programming Language :: Python :: 3.10
Classifier: Programming Language :: Python :: 3.11
Requires-Python: >=3.8
Requires-Dist: biolmai
Requires-Dist: jupyter-server>=2.0.0
Requires-Dist: jupyterlab<5,>=4.0.0
Provides-Extra: dev
Requires-Dist: jupyterlab<5,>=4.0.0; extra == 'dev'
Requires-Dist: pytest; extra == 'dev'
Requires-Dist: pytest-jupyter[server]>=0.5.0; extra == 'dev'
